tigr81/__init__.py
tigr81/main.py
tigr81/commands/__init__.py
tigr81/commands/core/__init__.py
tigr81/commands/core/gitw.py
tigr81/commands/core/poetry_pm.py
tigr81/commands/core/scaffold.py
tigr81/commands/hub/__init__.py
tigr81/commands/hub/helpers.py
tigr81/commands/hub/hub.py
tigr81/commands/hub/models.py
tigr81/commands/monorepo/__init__.py
tigr81/commands/monorepo/constants.py
tigr81/commands/monorepo/manifest.py
tigr81/commands/monorepo/monorepo.py
tigr81/commands/scaffold/__init__.py
tigr81/commands/scaffold/project_template.py
tigr81/commands/scaffold/scaffold.py
tigr81/commands/scaffold/select_project_type_interactive.py
tigr81/resources/hubs/primereact_examples.yml
tigr81/resources/hubs/tigr81_hub_templates.yml
tigr81/utils/__init__.py
tigr81/utils/extract_template_name.py
tigr81/utils/interactive_prompt.py
tigr81/utils/pretty.py
tigr81/utils/read_yaml.py
tigr81/utils/str_enum.py
tigr81-1.3.1.dist-info/METADATA
tigr81-1.3.1.dist-info/WHEEL
tigr81-1.3.1.dist-info/entry_points.txt
tigr81-1.3.1.dist-info/RECORD
