Metadata-Version: 2.4
Name: tigr81
Version: 1.3.1
Summary: Project scaffolder for humans.
Author-email: Giuseppe Ambrosio <giuambro97@gmail.com>
Requires-Python: <4,>=3.9
Requires-Dist: cookiecutter<3.0.0,>=2.4.0
Requires-Dist: copier<10.0.0,>=9.4.1
Requires-Dist: email-validator>=2.0.0.post2
Requires-Dist: graphviz<0.21.0,>=0.20.1
Requires-Dist: inquirerpy<0.4.0,>=0.3.4
Requires-Dist: pydantic<3.0.0,>=2.4.2
Requires-Dist: pyyaml<7.0.0,>=6.0.1
Requires-Dist: typer<0.21.0,>=0.20.0
Provides-Extra: dev
Requires-Dist: black<24.0.0,>=23.9.1; extra == 'dev'
Requires-Dist: mypy<2.0.0,>=1.5.1; extra == 'dev'
Requires-Dist: ruff<0.8.0,>=0.7.1; extra == 'dev'
Provides-Extra: test
Requires-Dist: pytest-cov<6.0.0,>=5.0.0; extra == 'test'
Requires-Dist: pytest-lazy-fixture<0.7.0,>=0.6.3; extra == 'test'
Requires-Dist: pytest-mock<4.0.0,>=3.14.0; extra == 'test'
Requires-Dist: pytest<8.0.0,>=7.4.2; extra == 'test'
